top.v
`timescale 1ns/1ps

//IR fields

`define oper_type   IR[31:27]
`define rdst        IR[26:22]
`define rsrc1       IR[21:17]
`define imm_mode    IR[16]
`define rsrc2       IR[15:11]
`define isrc        IR[15:0]

//arithmetic operation

`define movsgpr 5'b00000 //all the data is in binary as IR needs to be binary as we are using readb instruction to read the code
`define mov     5'b00001
`define add     5'b00010
`define sub     5'b00011
`define mul     5'b00100

//logical operation

`define ror     5'b00101
`define rand    5'b00110
`define rxor    5'b00111
`define rxnor   5'b01000
`define rnand   5'b01001
`define rnor    5'b01010
`define rnot    5'b01011

//load and store instruction for data memory

`define storereg    5'b01101 //store content of register in data memory
`define storedin    5'b01101 //store content of din bus(external) in data memory
`define senddout    5'b01111 //send data from data memory to dout bus (external)
`define sendreg     5'b10001 //send data from data memory to register

//jumping and branch instructions

`define jump        5'b10010
`define jcarry      5'b10011
`define jnocarry    5'b10100
`define jsign       5'b10101
`define jnosign     5'b10110
`define jzero       5'b10111
`define jnozero     5'b11000
`define joverflow   5'b11001
`define jnooverflow 5'b11010

//halt

`define halt    5'b11011 //won't come out of halt unless reset

module top(
    input clk, sys_rst,
    input [15:0] din,
    output reg [15:0] dout
); // clk-synchronisation signal, sys_rst-system reset, din-16 bit data that can be loaded from external world

//adding program and data memory
reg [31:0] inst_mem [15:0]; //program memory: (depth)16 elements of - 32 bit instructions (= size of IR)
reg [15:0] data_mem [15:0]; //data memory: 16 - 16 bit data = 4 nibbles
//following harvard architecture


reg [31:0] IR; //IR: 31-27 oper type, 26-22 dest reg, 21-17 src reg, 16 mode, 15-11 src2 or imm, 10-0 unused

//allows 32 (3 operand) operations involving 32 possible registers in register or immediate mode

reg [15:0] GPR [31:0]; //32 - 16 bit regsters

reg [15:0] SGPR;
reg [31:0] mul_res; //temporary register

reg sign =0, zero =0, overflow=0, carry=0;
reg [16:0] temp_sum; //for carry a 17 bit register used in carry flag

reg jmp_flag = 0; //to check if any jump has occurred 
reg stop = 0; //for halt



task decode_inst(); //task used instead of multiple always blocks
begin

    jmp_flag = 1'b0;
    stop = 1'b0;

    case (`oper_type)
    
    `movsgpr : 
    begin
        GPR [`rdst] = SGPR;
    end

    `mov : 
    begin
        if (`imm_mode)
        GPR [`rdst] = `isrc; //immediate mode
        else
        GPR [`rdst] = GPR [`rsrc1];
    end

    `add:
    begin
        if(`imm_mode)
        GPR [`rdst]=GPR [`rsrc1] + `isrc;
        else
        GPR [`rdst]=GPR [`rsrc1] + GPR [`rsrc2];
    end

    `sub:
    begin
        if(`imm_mode)
        GPR [`rdst]=GPR [`rsrc1] - `isrc;
        else
        GPR [`rdst]=GPR [`rsrc1] - GPR [`rsrc2];
    end

    `mul:
    begin
        if(`imm_mode)
        mul_res=GPR [`rsrc1] * `isrc;
        else
        mul_res=GPR [`rsrc1] * GPR [`rsrc2];

        GPR [`rdst] = mul_res [15:0];
        SGPR = mul_res [31:16];
    end

    `ror:
    begin
        if(`imm_mode)
        GPR[`rdst]=GPR[`rsrc1] | `isrc;
        else
        GPR[`rdst]=GPR[`rsrc1] | GPR[`rsrc2];
    end

    `rand:
    begin
        if(`imm_mode)
        GPR[`rdst]=GPR[`rsrc1] & `isrc;
        else
        GPR[`rdst]=GPR[`rsrc1] & GPR[`rsrc2];
    end

    `rxor:
    begin
        if(`imm_mode)
        GPR[`rdst]=GPR[`rsrc1] ^ `isrc;
        else
        GPR[`rdst]=GPR[`rsrc1] ^ GPR[`rsrc2];
    end

    `rxnor:
    begin
        if(`imm_mode)
        GPR[`rdst]=GPR[`rsrc1] ~^ `isrc;
        else
        GPR[`rdst]=GPR[`rsrc1] ~^ GPR[`rsrc2];
    end

    `rnand:
    begin
        if(`imm_mode)
        GPR[`rdst]= ~(GPR[`rsrc1] & `isrc);
        else
        GPR[`rdst]= ~(GPR[`rsrc1] & GPR[`rsrc2]);
    end

    `rnor:
    begin
        if(`imm_mode)
        GPR[`rdst]= ~(GPR[`rsrc1] | `isrc);
        else
        GPR[`rdst]= ~(GPR[`rsrc1] | GPR[`rsrc2]);
    end

    `rnot:
    begin
        if(`imm_mode)
        GPR[`rdst]= ~(`isrc);
        else
        GPR[`rdst]= ~(GPR[`rsrc1]);
    end

    `storedin:
    begin
        data_mem [`isrc] = din; //address in data memory specified by immeidate address, thus can access 64kb memory
    end

    `storereg:
    begin
        data_mem[`isrc] = GPR [`rsrc1];
    end

    `senddout:
    begin
        dout = data_mem[`isrc];
    end

    `sendreg:
    begin
        GPR[`rdst] = data_mem[`isrc];
    end

    `jump:
    begin
        jmp_flag = 1'b1;
    end

    `jcarry: 
    begin
        if (carry == 1'b1)
        jmp_flag= 1'b1;
        else
        jmp_flag = 1'b0;
    end

    `jsign: 
    begin
        if (sign == 1'b1)
        jmp_flag= 1'b1;
        else
        jmp_flag = 1'b0;
    end

    `jzero: 
    begin
        if (zero == 1'b1)
        jmp_flag= 1'b1;
        else
        jmp_flag = 1'b0;
    end

    `joverflow: 
    begin
        if (overflow == 1'b1)
        jmp_flag= 1'b1;
        else
        jmp_flag = 1'b0;
    end

    `jnocarry: 
    begin
        if (carry == 1'b0)
        jmp_flag= 1'b1;
        else
        jmp_flag = 1'b0;
    end

    `jnosign: 
    begin
        if (sign == 1'b0)
        jmp_flag= 1'b1;
        else
        jmp_flag = 1'b0;
    end

    `jnozero: 
    begin
        if (zero == 1'b0)
        jmp_flag= 1'b1;
        else
        jmp_flag = 1'b0;
    end

    `jnooverflow: 
    begin
        if (overflow == 1'b0)
        jmp_flag= 1'b1;
        else
        jmp_flag = 1'b0;
    end

    `halt : 
    begin
        stop = 1'b1;
    end


    endcase
end
endtask



//checking for four flags - sign, zero, carry and overflow

task decode_condflag();
begin
    //sign
    if (`oper_type ==`mul)
    sign = SGPR[15];
    else
    sign = GPR[`rdst][15];

    //carry
    if (`oper_type ==`add)
    begin
        if (`imm_mode)
        begin
            temp_sum = GPR[`rsrc1]+`isrc;
            carry = temp_sum [16];
        end
        else
        begin
            temp_sum = GPR[`rsrc1]+GPR[`rsrc2];
            carry = temp_sum [16];
        end

    end
    else
    begin
        carry = 1'b0;
    end

    //zero
    if (`oper_type == `mul)
    zero = ~( (|SGPR) | (|GPR [`rdst]));
    else
    zero = ~(|GPR[`rdst]);

    //overflow
    if(`oper_type == `add)
    begin
        if (`imm_mode)
        overflow = ( (~GPR[`rsrc1][15]) & ~IR[15] & GPR[`rdst][15]) | ( (GPR[`rsrc1][15]) & IR[15] & ~GPR[`rdst][15]);
        else
        overflow = ( (~GPR[`rsrc1][15]) & ~GPR[`rsrc2][15] & GPR[`rdst][15]) | ( (GPR[`rsrc1][15]) & GPR[`rsrc2][15] & ~GPR[`rdst][15]);
    end

    else if (`oper_type == `sub)
    begin
        if (`imm_mode)
        overflow = ( (~GPR[`rsrc1][15]) & IR[15] & GPR[`rdst][15]) | ( (GPR[`rsrc1][15]) & ~IR[15] & ~GPR[`rdst][15]);
        else
        overflow = ( (~GPR[`rsrc1][15]) & GPR[`rsrc2][15] & GPR[`rdst][15]) | ( (GPR[`rsrc1][15]) & ~GPR[`rsrc2][15] & ~GPR[`rdst][15]);
    end

    else
    begin
        overflow = 1'b0;
    end
end
endtask

//reading program

initial 
begin
    $readmemb ("inst_mem.mem",inst_mem); //reading binary data from file
end

reg [2:0] count =0;
integer PC = 0; //programme counter which points to the next instruction in a mup

//reading instructions one after the other
always @ (posedge clk)
begin
    if (sys_rst)
    begin 
        count<=0;
        PC<=0;
    end
    else
    begin
        if (count<4)
        begin
            count <= count +1;
        end
        else
        begin
            count<=0;
            PC <= PC +1; //waits for 4 clock ticks before reading the next instruction
        end
    end


end

//reading instrcutions
always @(*)
begin
    if (sys_rst == 1'b1)
    IR = 0;
    else
    begin
        IR = inst_mem[PC];
        decode_inst();
        decode_condflag();
    end
end

//fsm for instruction fetch -> decode -> delay -> next instruction -> check halt -> instrcution fetch

parameter idle = 0, fetch_inst = 1, dec_exec_inst = 2, next_inst = 3, sense_halt = 4, delay_next_inst = 5;
//idle: checks reset
//fetch_inst: loads instruction from program memory
//dec_exec_inst: execute instruction + update condition flag
//next_inst: next instruction is fetched

reg[2:0] state = idle, next_state = idle;
//fsm states

//reset decoder
always @ (posedge clk)
begin
    if (sys_rst)
    state<= idle;
    else
    state <= next_state;
end

//next state decoder + output decoder

always @ (*)
begin
    case (state)
    idle: 
    begin
        IR = 32'b0;
        PC = 0;
        next_state = fetch_inst;
    end

    fetch_inst:
    begin
        IR = inst_mem [PC];
        next_state = dec_exec_inst;
    end

    dec_exec_inst: 
    begin
        decode_inst();
        decode_condflag();
        next_state = delay_next_inst;
    end

    delay_next_inst:
    begin
        if (count < 4)
        next_state = delay_next_inst;
        else
        next_state = next_inst
    end

    next_inst:
    begin
        next_state = sense_halt;
        if (jmp_flag==1'b1)
        PC = `isrc;
        else
        PC = PC + 1;
    end

    sense_halt: 
    begin
        if (stop == 1'b0)
        next_state = fetch_inst;
        else if (sys_rst == 1'b1)
        next_state = idle;
        else
        next_state = sense_halt;
    end

    default : next_state = idle;
    endcase
end

//count update for delay

always @ (posedge clk)
begin
    case (state)

    idle: 
    begin
        count<=0;
    end

    fetch_inst: 
    begin
        count<=0;
    end

    dec_exec_inst: 
    begin
        count<=0;
    end

    delay_next_inst: 
    begin
        count<=count+1;
    end

    next_inst: 
    begin
        count<=0;
    end

    sense_halt: 
    begin
        count<=0;
    end

    default: count<=0;

    endcase
end


endmodule

top_tb.v
`timescale 1ns/1ps

//IR fields

`define oper_type   IR[31:27]
`define rdst        IR[26:22]
`define rsrc1       IR[21:17]
`define imm_mode    IR[16]
`define rsrc2       IR[15:11]
`define isrc        IR[15:0]

//arithmetic operation

`define movsgpr 5'b00000
`define mov     5'b00001
`define add     5'b00010
`define sub     5'b00011
`define mul     5'b00100

//logical operation

`define ror     5'b00101
`define rand    5'b00110
`define rxor    5'b00111
`define rxnor   5'b01000
`define rnand   5'b01001
`define rnor    5'b01010
`define rnot    5'b01011

//load and store instruction

`define storereg    5'b01101 //store content of register in data memory
`define storedin    5'b01101 //store content of din bus(external) in data memory
`define senddout    5'b01111 //send data from data memory to dout bus (external)
`define sendreg     5'b10001 //send data from data memory to register

`define jump        5'b10010
`define jcarry      5'b10011
`define jnocarry    5'b10100
`define jsign       5'b10101
`define jnosign     5'b10110
`define jzero       5'b10111
`define jnozero     5'b11000
`define joverflow   5'b11001
`define jnooverflow 5'b11010

`include "top.v"

module top_tb;

integer i = 0; //to count elements

reg clk = 0, sys_rst = 0;
reg [15:0] din = 0;
wire [15:0] dout;

top dut (clk, sys_rst, din, dout); //dut is the instance name

always #5 clk = ~clk;

initial 
begin

    $dumpfile("top_tb.vcd");
    $dumpvars(0,top_tb);

    sys_rst = 1'b1;
    repeat (5) @(posedge clk);
    sys_rst = 1'b0;
    #800;
    $stop;


end

endmodule

top_tb.vcd
$date
	Wed Jun 14 12:53:35 2023
$end
$version
	Icarus Verilog
$end
$timescale
	1ps
$end
$scope module top_tb $end
$var integer 32 ! i [31:0] $end
$scope module dut $end
$var reg 32 " IR [31:0] $end
$var reg 16 # SGPR [15:0] $end
$var reg 1 $ carry $end
$var reg 32 % mul_res [31:0] $end
$var reg 1 & overflow $end
$var reg 1 ' sign $end
$var reg 17 ( temp_sum [16:0] $end
$var reg 1 ) zero $end
$upscope $end
$upscope $end
$enddefinitions $end
#0
$dumpvars
0)
b110 (
0'
0&
bx %
0$
bx #
b10000000001010000000000000100 "
b100000 !
$end
#10000
b100 (
b10000000010000010100000000000 "
#20000
b1001000000010000000000110111 "
#30000
b1001000011100000000000000000 "
#40000
1)
b110001000011110000000000111000 "
#50000
0)
b111001000011110000000000111000 "
#60000
1)
b0 (
b10000100000000000100000000000 "
#70000
0)
b1000000000000000 (
1'
b10000100000000000100000000000 "
#80000
1&
1$
b10000000000000010 (
0'
b10000100000000000100000000000 "
#90000
0&
0$
b1000000000000000 (
1'
b10000100000000000100000000000 "
